{
  "parent": "minecraft:recipes/root",
  "criteria": {
    "has_flintstone_bricks": {
      "conditions": {
        "items": [
          {
            "items": "desire:flintstone_bricks"
          }
        ]
      },
      "trigger": "minecraft:inventory_changed"
    },
    "has_the_recipe": {
      "conditions": {
        "recipe": "desire:flintstone_brick_slab"
      },
      "trigger": "minecraft:recipe_unlocked"
    }
  },
  "requirements": [
    [
      "has_the_recipe",
      "has_flintstone_bricks"
    ]
  ],
  "rewards": {
    "recipes": [
      "desire:flintstone_brick_slab"
    ]
  }
}